deep_disfluency/__init__.py
deep_disfluency/asr/__init__.py
deep_disfluency/asr/ibm_watson.py
deep_disfluency/corpus/BNC_create_corpus.py
deep_disfluency/corpus/BNC_swda_POS_converter.py
deep_disfluency/corpus/__init__.py
deep_disfluency/corpus/create_fake_timing_corpus.py
deep_disfluency/corpus/create_folds.py
deep_disfluency/corpus/disfluency_corpus_creator.py
deep_disfluency/corpus/load.py
deep_disfluency/corpus/repair.py
deep_disfluency/corpus/selfrepair_annotation.py
deep_disfluency/corpus/spelling_dictionary.py
deep_disfluency/corpus/swda.py
deep_disfluency/corpus/tree_pos_map.py
deep_disfluency/corpus/tree_pos_map_writer.py
deep_disfluency/corpus/util.py
deep_disfluency/data/lm_corpora/swbd_disf_heldout_clean.text
deep_disfluency/data/lm_corpora/swbd_disf_heldout_edit.text
deep_disfluency/data/lm_corpora/swbd_disf_test_clean.text
deep_disfluency/data/lm_corpora/swbd_disf_test_edit.text
deep_disfluency/data/lm_corpora/swbd_disf_train_1_2_clean.text
deep_disfluency/data/lm_corpora/swbd_disf_train_1_2_edit.text
deep_disfluency/data/lm_corpora/swbd_disf_train_1_clean.text
deep_disfluency/data/lm_corpora/swbd_disf_train_1_edit.text
deep_disfluency/data/tag_representations/swbd_dact_interactive_tag_corpus.csv
deep_disfluency/data/tag_representations/swbd_dact_interactive_tags.csv
deep_disfluency/data/tag_representations/swbd_dact_tag_corpus.csv
deep_disfluency/data/tag_representations/swbd_dact_tags.csv
deep_disfluency/data/tag_representations/swbd_dact_uttseg_interactive_tag_corpus.csv
deep_disfluency/data/tag_representations/swbd_dact_uttseg_interactive_tags.csv
deep_disfluency/data/tag_representations/swbd_disf1_021_tags.csv
deep_disfluency/data/tag_representations/swbd_disf1_039_tags.csv
deep_disfluency/data/tag_representations/swbd_disf1_041_tags.csv
deep_disfluency/data/tag_representations/swbd_disf1_rpMid_tags.csv
deep_disfluency/data/tag_representations/swbd_disf1_simple_tag_corpus.csv
deep_disfluency-0.0.1.dist-info/METADATA
deep_disfluency-0.0.1.dist-info/RECORD
deep_disfluency-0.0.1.dist-info/WHEEL
deep_disfluency-0.0.1.dist-info/top_level.txt
