Metadata-Version: 2.1
Name: deep-disfluency
Version: 0.0.1
Summary: Deep Learning systems for training and testing disfluency detection and related tasks on speech data.
Home-page: https://github.com/dsg-bielefeld/deep_disfluency
Author: Julian Hough, Tom Gurion, David Schlangen
Author-email: julianchough@gmail.com
License: UNKNOWN
Keywords: disfluency detection utterance segmentation deep machine learning
Platform: UNKNOWN
Classifier: Development Status :: 3 - Alpha
Classifier: Intended Audience :: Science/Research
Classifier: Intended Audience :: Telecommunications Industry
Classifier: Topic :: Multimedia :: Sound/Audio :: Speech
Classifier: Topic :: Scientific/Engineering :: Artificial Intelligence
Classifier: Topic :: Scientific/Engineering :: Human Machine Interfaces
Classifier: License :: OSI Approved :: MIT License
Classifier: Programming Language :: Python :: 2
Classifier: Programming Language :: Python :: 2.7
Requires-Dist: numpy
Requires-Dist: scipy
Requires-Dist: pandas
Requires-Dist: theano
Requires-Dist: scikit-learn
Requires-Dist: gensim
Requires-Dist: nltk
Requires-Dist: python-crfsuite
Requires-Dist: fluteline
Requires-Dist: watson-streaming
